{"name":"Successful login with valid credentials of a registered user","id":"user-authentication;successful-login-with-valid-credentials-of-a-registered-user","scenarioId":"login:Successful login with valid credentials of a registered user","methodName":"Successful login with valid credentials of a registered user","testSteps":[{"number":1,"description":"Given that doctor wants to log in to the system","duration":54,"startTime":"2025-07-11T14:30:16.629364996-05:00[America/Bogota]","result":"SUCCESS","precondition":false,"level":0},{"number":2,"description":"Given that doctor is on the login page","duration":1652,"startTime":"2025-07-11T14:30:16.684681417-05:00[America/Bogota]","result":"SUCCESS","precondition":false,"level":0,"children":[{"number":3,"description":"Doctor open the","duration":1507,"startTime":"2025-07-11T14:30:16.824355542-05:00[America/Bogota]","result":"SUCCESS","precondition":false,"level":1,"children":[{"number":4,"description":"doctor opens the Login page","duration":1485,"startTime":"2025-07-11T14:30:16.840307478-05:00[America/Bogota]","result":"SUCCESS","precondition":false,"level":2}]}]},{"number":5,"description":"When he enters the valid credentials\n| user | password |\n| carlos.santana@example.com | medico1234 |","duration":462,"startTime":"2025-07-11T14:30:18.337613534-05:00[America/Bogota]","result":"SUCCESS","precondition":false,"level":0,"children":[{"number":6,"description":"Doctor login","duration":448,"startTime":"2025-07-11T14:30:18.348417541-05:00[America/Bogota]","result":"SUCCESS","precondition":false,"level":1,"children":[{"number":7,"description":"doctor enters \u0027carlos.santana@example.com\u0027 into Campo de Correo Electrónico","duration":192,"startTime":"2025-07-11T14:30:18.381278598-05:00[America/Bogota]","result":"SUCCESS","precondition":false,"level":2},{"number":8,"description":"doctor enters \u0027medico1234\u0027 into Campo de Contraseña","duration":100,"startTime":"2025-07-11T14:30:18.574425285-05:00[America/Bogota]","result":"SUCCESS","precondition":false,"level":2},{"number":9,"description":"doctor clicks on Botón Aceptar","duration":116,"startTime":"2025-07-11T14:30:18.676504185-05:00[America/Bogota]","result":"SUCCESS","precondition":false,"level":2}]}]},{"number":10,"description":"Then he should see the main page of the application","duration":372,"startTime":"2025-07-11T14:30:18.800251911-05:00[America/Bogota]","result":"FAILURE","precondition":false,"level":0,"children":[{"number":11,"description":"Then the home page should be (true)","duration":308,"startTime":"2025-07-11T14:30:18.855204613-05:00[America/Bogota]","screenshots":[{"screenshot":"e1768db9e6367bd00a5a37f812d9ac5879e40b67db4a0ef8d3b4e04864d7abd0.png","htmlSource":"pagesource1058386441934797315.html","timeStamp":1752262219160,"screenshotName":"e1768db9e6367bd00a5a37f812d9ac5879e40b67db4a0ef8d3b4e04864d7abd0.png"}],"exception":{"errorType":"java.lang.AssertionError","message":"\nExpected: is \u003ctrue\u003e\n     but: was \u003cfalse\u003e","stackTrace":[{"declaringClass":"co.edu.udea.calidad.citasSalud.stepdefinitions.LoginStepDefinitions","methodName":"heShouldSeeTheMainPageOfTheApplication","fileName":"LoginStepDefinitions.java","lineNumber":56},{"declaringClass":"worker.org.gradle.process.internal.worker.GradleWorkerMain","methodName":"run","fileName":"GradleWorkerMain.java","lineNumber":69},{"declaringClass":"worker.org.gradle.process.internal.worker.GradleWorkerMain","methodName":"main","fileName":"GradleWorkerMain.java","lineNumber":74}]},"result":"FAILURE","precondition":false,"level":1}]}],"userStory":{"id":"login","storyName":"User Authentication","displayName":"User Authentication","path":"login","pathElements":[{"name":"login","description":""}],"narrative":"  As a system user\n  I want to be able to log in with my credentials\n  To access the features corresponding to my profile","type":"feature"},"title":"Successful login with valid credentials of a registered user","description":"","backgroundTitle":"","backgroundDescription":"","tags":[{"name":"Linux","type":"context","displayName":"Linux"},{"name":"Chrome","type":"context","displayName":"Chrome"},{"name":"login","type":"tag","displayName":"login"},{"name":"smoke","type":"tag","displayName":"smoke"},{"name":"Chrome, Linux","type":"context","displayName":"Chrome, Linux"}],"startTime":"2025-07-11T14:30:16.566433766-05:00[America/Bogota]","duration":115,"testFailureCause":{"errorType":"java.lang.AssertionError","message":"\nExpected: is \u003ctrue\u003e\n     but: was \u003cfalse\u003e","stackTrace":[{"declaringClass":"co.edu.udea.calidad.citasSalud.stepdefinitions.LoginStepDefinitions","methodName":"heShouldSeeTheMainPageOfTheApplication","fileName":"LoginStepDefinitions.java","lineNumber":56},{"declaringClass":"worker.org.gradle.process.internal.worker.GradleWorkerMain","methodName":"run","fileName":"GradleWorkerMain.java","lineNumber":69},{"declaringClass":"worker.org.gradle.process.internal.worker.GradleWorkerMain","methodName":"main","fileName":"GradleWorkerMain.java","lineNumber":74}]},"testFailureClassname":"java.lang.AssertionError","testFailureMessage":"\nExpected: is \u003ctrue\u003e\n     but: was \u003cfalse\u003e","testFailureSummary":"FAILURE;java.lang.AssertionError;\nExpected: is \u003ctrue\u003e\n     but: was \u003cfalse\u003e;LoginStepDefinitions.java","projectKey":"","annotatedResult":"FAILURE","sessionId":"6f7b58b9cceffc6cac8c1634f5d8dc8b","driver":"chrome:doctor","isManualTestingUpToDate":false,"context":"chrome,linux","manual":false,"testSource":"Cucumber","actors":[{"name":"doctor","can":["browse the web"]}],"order":0,"result":"FAILURE"}